README.md
setup.cfg
setup.py
tf_data/ImagePatches.py
tf_data/LabeledImageDataset.py
tf_data/__init__.py
tf_data/drive.py
tf_data.egg-info/PKG-INFO
tf_data.egg-info/SOURCES.txt
tf_data.egg-info/dependency_links.txt
tf_data.egg-info/requires.txt
tf_data.egg-info/top_level.txt