Metadata-Version: 1.1
Name: tf-data
Version: 0.0.4
Summary: Easy datasets for tensorflow
Home-page: https://github.com/fru/tf_data
Author: Florian Rueberg
Author-email: florian.rueberg@gmail.com
License: UNKNOWN
Download-URL: https://github.com/fru/tf_data/archive/0.0.4.tar.gz
Keywords: datasets,tensorflow
Platform: UNKNOWN
